iotile_support_lib_controller_3/__init__.py
iotile_support_lib_controller_3/configmanager.py
iotile_support_lib_controller_3/controllertest.py
iotile_support_lib_controller_3/firmware_image_analyzer.py
iotile_support_lib_controller_3/remotebridge.py
iotile_support_lib_controller_3/sensorgraph.py
iotile_support_lib_controller_3/tilemanager.py
iotile_support_lib_controller_3/data/pingpong_exec_bundle.hex
iotile_support_lib_controller_3/data/s112_nrf52_6.1.1_softdevice.hex
iotile_support_lib_controller_3/lib_controller_types/__init__.py
iotile_support_lib_controller_3/lib_controller_types/fw_configvariable.py
iotile_support_lib_controller_3/lib_controller_types/fw_graphnode.py
iotile_support_lib_controller_3/lib_controller_types/fw_reading.py
iotile_support_lib_controller_3/lib_controller_types/fw_stream.py
iotile_support_lib_controller_3/lib_controller_types/fw_streamerstatus.py
iotile_support_lib_controller_3/lib_controller_types/fw_tiledescriptor.py
iotile_support_lib_controller_3/lib_controller_types/fw_tileselector.py
iotile_support_lib_controller_3-3.8.5.dist-info/METADATA
iotile_support_lib_controller_3-3.8.5.dist-info/WHEEL
iotile_support_lib_controller_3-3.8.5.dist-info/entry_points.txt
iotile_support_lib_controller_3-3.8.5.dist-info/top_level.txt
iotile_support_lib_controller_3-3.8.5.dist-info/RECORD
